ng_link/__init__.py
ng_link/dispim_link.py
ng_link/exaspim_link.py
ng_link/iSPIM_top.py
ng_link/link_utils.py
ng_link/ng_layer.py
ng_link/ng_state.py
ng_link/parsers.py
ng_link/raw_link.py
ng_link/scripts/ccf_ref.csv
ng_link/scripts/create_compressed_segmentation_precompute.py
ng_link/scripts/create_links.py
ng_link/scripts/create_mesh_precompute.py
ng_link/scripts/curate_links.py
ng_link/scripts/generate_cff_cell_count.py
ng_link/utils/__init__.py
ng_link/utils/shader_utils.py
ng_link/utils/transfer.py
ng_link/utils/utils.py
aind_ng_link-1.0.17.dist-info/LICENSE
aind_ng_link-1.0.17.dist-info/METADATA
aind_ng_link-1.0.17.dist-info/WHEEL
aind_ng_link-1.0.17.dist-info/top_level.txt
aind_ng_link-1.0.17.dist-info/RECORD
