Metadata-Version: 2.1
Name: aind-ng-link
Version: 1.0.17
Summary: Python package for the generation of neuroglancer links
Author-email: David Feng <david.feng@alleninstitute.org>, Sharmishtaa Seshamani <sharmishtaas@alleninstitute.org>, Camilo Laiton <camilo.laiton@alleninstitute.org>
License: MIT
Classifier: Programming Language :: Python :: 3
Requires-Python: >=3.8
License-File: LICENSE
Requires-Dist: pandas
Requires-Dist: sphinx
Requires-Dist: pint >=0.18
Requires-Dist: numpy >=1.21.6
Requires-Dist: neuroglancer >=2.36
Requires-Dist: xmltodict >=0.13.0
Requires-Dist: zarr
Requires-Dist: s3fs
Requires-Dist: boto3
Provides-Extra: dev
Requires-Dist: black ; extra == 'dev'
Requires-Dist: coverage ; extra == 'dev'
Requires-Dist: flake8 ; extra == 'dev'
Requires-Dist: interrogate ; extra == 'dev'
Requires-Dist: isort ; extra == 'dev'
Requires-Dist: Sphinx ; extra == 'dev'
Requires-Dist: pygit2 ; extra == 'dev'
